cyber_skyline/chall_parser/__init__.py
cyber_skyline/chall_parser/py.typed
cyber_skyline/chall_parser/rewriter.py
cyber_skyline/chall_parser/template.py
cyber_skyline/chall_parser/warnings.py
cyber_skyline/chall_parser/yaml_parser.py
cyber_skyline/chall_parser/compose/__init__.py
cyber_skyline/chall_parser/compose/answer.py
cyber_skyline/chall_parser/compose/challenge_info.py
cyber_skyline/chall_parser/compose/compose.py
cyber_skyline/chall_parser/compose/network.py
cyber_skyline/chall_parser/compose/service.py
cyber_skyline/chall_parser/compose/types.py
cyber_skyline/chall_parser/compose/validators.py
cyber_skyline_chall_parser-0.5.1.dist-info/licenses/LICENSE
cyber_skyline_chall_parser-0.5.1.dist-info/METADATA
cyber_skyline_chall_parser-0.5.1.dist-info/WHEEL
cyber_skyline_chall_parser-0.5.1.dist-info/top_level.txt
cyber_skyline_chall_parser-0.5.1.dist-info/RECORD
