Metadata-Version: 2.4
Name: cyber-skyline-chall-parser
Version: 0.5.1
Summary: Parser library for handling the specialized challenge docker compose format
Author-email: John Marsden <research@johnmarsden.dev>
Requires-Python: >=3.12
License-File: LICENSE
Requires-Dist: attrs==25.3.0
Requires-Dist: cattrs==25.2.0
Requires-Dist: faker>=37.4.0
Requires-Dist: pyyaml>=6.0.2
Dynamic: license-file
